CMakeLists.txt
FindBob.cmake
LICENSE
MANIFEST.in
README.rst
bootstrap-buildout.py
buildout.cfg
requirements.txt
setup.py
test.cpp
test.png
test.py
version.txt
bob.example.cmake.egg-info/PKG-INFO
bob.example.cmake.egg-info/SOURCES.txt
bob.example.cmake.egg-info/dependency_links.txt
bob.example.cmake.egg-info/entry_points.txt
bob.example.cmake.egg-info/requires.txt
bob.example.cmake.egg-info/top_level.txt
bob.example.cmake.egg-info/zip-safe