Metadata-Version: 1.1
Name: bob.example.cmake
Version: 1.0.1
Summary: Example project using Bob C++ interface
Home-page: https://github.com/bioidiap/bob.example.cmake
Author: Manuel Guenther
Author-email: manuel.guenther@idiap.ch
License: GPLv3
Platform: UNKNOWN
Classifier: Framework :: Bob
Classifier: Development Status :: 4 - Beta
Classifier: License :: OSI Approved :: GNU General Public License v3 (GPLv3)
Classifier: Intended Audience :: Education
Classifier: Intended Audience :: Science/Research
Classifier: Natural Language :: English
Classifier: Programming Language :: Python
Classifier: Programming Language :: Python :: 3
